teyaotlani/__init__.py
teyaotlani/__main__.py
teyaotlani/client/__init__.py
teyaotlani/client/protocol.py
teyaotlani/client/session.py
teyaotlani/content/__init__.py
teyaotlani/content/gemtext.py
teyaotlani/protocol/__init__.py
teyaotlani/protocol/constants.py
teyaotlani/protocol/request.py
teyaotlani/protocol/response.py
teyaotlani/protocol/status.py
teyaotlani/py.typed
teyaotlani/server/__init__.py
teyaotlani/server/config.py
teyaotlani/server/handler.py
teyaotlani/server/middleware.py
teyaotlani/server/protocol.py
teyaotlani/server/server.py
teyaotlani/utils/__init__.py
teyaotlani/utils/logging.py
teyaotlani/utils/url.py
teyaotlani-0.1.4.dist-info/WHEEL
teyaotlani-0.1.4.dist-info/entry_points.txt
teyaotlani-0.1.4.dist-info/METADATA
teyaotlani-0.1.4.dist-info/RECORD
